{"formautofill@mozilla.org":{"permissions":["internal:svgContextPropertiesAllowed","internal:privateBrowsingAllowed"],"origins":[]},"pictureinpicture@mozilla.org":{"permissions":["internal:svgContextPropertiesAllowed","internal:privateBrowsingAllowed"],"origins":[]},"screenshots@mozilla.org":{"permissions":["internal:svgContextPropertiesAllowed","internal:privateBrowsingAllowed"],"origins":[]},"webcompat@mozilla.org":{"permissions":["internal:svgContextPropertiesAllowed","internal:privateBrowsingAllowed"],"origins":[]},"default-theme@mozilla.org":{"permissions":["internal:svgContextPropertiesAllowed"],"origins":[]},"addons-search-detection@mozilla.com":{"permissions":["internal:svgContextPropertiesAllowed","internal:privateBrowsingAllowed"],"origins":[]},"google@search.mozilla.org":{"permissions":["internal:svgContextPropertiesAllowed","internal:privateBrowsingAllowed"],"origins":[]},"wikipedia@search.mozilla.org":{"permissions":["internal:svgContextPropertiesAllowed","internal:privateBrowsingAllowed"],"origins":[]},"bing@search.mozilla.org":{"permissions":["internal:svgContextPropertiesAllowed","internal:privateBrowsingAllowed"],"origins":[]},"ddg@search.mozilla.org":{"permissions":["internal:svgContextPropertiesAllowed","internal:privateBrowsingAllowed"],"origins":[]},"ebay@search.mozilla.org":{"permissions":["internal:svgContextPropertiesAllowed","internal:privateBrowsingAllowed"],"origins":[]},"firefox-compact-dark@mozilla.org":{"permissions":["internal:privateBrowsingAllowed"],"origins":[]},"extension@tabliss.io":{"permissions":["internal:privateBrowsingAllowed"],"origins":[]},"uBlock0@raymondhill.net":{"permissions":["internal:privateBrowsingAllowed"],"origins":[]},"addon@darkreader.org":{"permissions":["internal:privateBrowsingAllowed"],"origins":[]},"{446900e4-71c2-419f-a6a7-df9c091e268b}":{"permissions":["internal:privateBrowsingAllowed"],"origins":[]},"{46104586-98c3-407e-a349-290c9ff3594d}":{"permissions":["internal:privateBrowsingAllowed"],"origins":[]},"idcac-pub@guus.ninja":{"permissions":["internal:privateBrowsingAllowed"],"origins":[]},"addons-restricted-domains@mozilla.com":{"permissions":["internal:svgContextPropertiesAllowed","internal:privateBrowsingAllowed"],"origins":[]},"sonarr-radarr-lidarr-autosearch@robgreen.me":{"permissions":["internal:privateBrowsingAllowed"],"origins":[]},"{036a55b4-5e72-4d05-a06c-cba2dfcc134a}":{"permissions":["internal:privateBrowsingAllowed"],"origins":[]}}